linxploit/__init__.py
linxploit/commands.py
linxploit/main.py
linxploit/utils.py
linxploit-0.1.2.dist-info/LICENSE
linxploit-0.1.2.dist-info/METADATA
linxploit-0.1.2.dist-info/WHEEL
linxploit-0.1.2.dist-info/entry_points.txt
linxploit-0.1.2.dist-info/top_level.txt
linxploit-0.1.2.dist-info/RECORD
