Metadata-Version: 2.1
Name: linxploit
Version: 0.1.2
Summary: A powerful Linux exploitation framework for ethical hacking
Home-page: https://github.com/darkshadow2bd/LinXploit
Author: DarkShadow
Author-email: darkshadow2bd@gmail.com
License: UNKNOWN
Platform: UNKNOWN
Classifier: Programming Language :: Python :: 3
Classifier: License :: OSI Approved :: MIT License
Classifier: Operating System :: POSIX :: Linux
Requires-Python: >=3.6
